selcuk_serverless_sdk_schema/__init__.py
selcuk_serverless_sdk_schema/schema/__init__.py
selcuk_serverless_sdk_schema/schema/serverless/__init__.py
selcuk_serverless_sdk_schema/schema/serverless/instrumentation/__init__.py
selcuk_serverless_sdk_schema/schema/serverless/instrumentation/tags/__init__.py
selcuk_serverless_sdk_schema/schema/serverless/instrumentation/tags/v1/__init__.py
selcuk_serverless_sdk_schema/schema/serverless/instrumentation/v1/__init__.py
selcuk_serverless_sdk_schema/tests/__init__.py
selcuk_serverless_sdk_schema/tests/test_schema.py
selcuk_serverless_sdk_schema-0.0.5.dist-info/METADATA
selcuk_serverless_sdk_schema-0.0.5.dist-info/WHEEL
selcuk_serverless_sdk_schema-0.0.5.dist-info/top_level.txt
selcuk_serverless_sdk_schema-0.0.5.dist-info/RECORD
