Metadata-Version: 2.1
Name: selcuk-serverless-sdk-schema
Version: 0.0.5
Summary: The protobuf generated Serverless SDK Schema
Author: selcuk_
Requires-Python: >=3.7
Requires-Dist: betterproto[compiler] (<3.0.0,>=2.0.0b5)
Requires-Dist: grpcio-tools (<2.0.0,>=1.51.1)
Requires-Dist: poethepoet (<1.0.0,>=0.17.1)
Requires-Dist: protobuf (>=4.21.12)
Requires-Dist: typing-extensions (>=4.4)
Provides-Extra: tests
Requires-Dist: black (>=22.12) ; extra == 'tests'
Requires-Dist: pytest (>=7.2) ; extra == 'tests'
Requires-Dist: ruff (>=0.0.199) ; extra == 'tests'
